adder/add_functions.py
tiny_python_functions_WQERFQW-1.0.0.dist-info/METADATA
tiny_python_functions_WQERFQW-1.0.0.dist-info/WHEEL
tiny_python_functions_WQERFQW-1.0.0.dist-info/entry_points.txt
tiny_python_functions_WQERFQW-1.0.0.dist-info/top_level.txt
tiny_python_functions_WQERFQW-1.0.0.dist-info/RECORD
