Metadata-Version: 2.1
Name: tiny-python-functions-WQERFQW
Version: 1.0.0
Summary: This is an exercise to publish smth on pipy
Home-page: https://github.com/realpython/reader
Author: myself
Author-email: info@myself.com
License: MIT
Platform: UNKNOWN
Classifier: License :: OSI Approved :: MIT License
Classifier: Programming Language :: Python :: 3
Classifier: Programming Language :: Python :: 3.8
Requires-Dist: feedparser
Requires-Dist: html2text
